mozinfo/__init__.py
mozinfo/mozinfo.py
mozinfo/string_version.py
mozinfo-1.2.1.dist-info/METADATA
mozinfo-1.2.1.dist-info/WHEEL
mozinfo-1.2.1.dist-info/entry_points.txt
mozinfo-1.2.1.dist-info/top_level.txt
mozinfo-1.2.1.dist-info/RECORD
